GaozhiliangCCBianchengZhinanLinrui/README.md
GaozhiliangCCBianchengZhinanLinrui/__init__.py
GaozhiliangCCBianchengZhinanLinrui/__main__.py
GaozhiliangCCBianchengZhinanLinrui/file.pdf
GaozhiliangCCBianchengZhinanLinrui/index.html
gaozhiliang_c_c_biancheng_zhinan_linrui-2024.3.2.0.dist-info/METADATA
gaozhiliang_c_c_biancheng_zhinan_linrui-2024.3.2.0.dist-info/WHEEL
gaozhiliang_c_c_biancheng_zhinan_linrui-2024.3.2.0.dist-info/entry_points.txt
gaozhiliang_c_c_biancheng_zhinan_linrui-2024.3.2.0.dist-info/top_level.txt
gaozhiliang_c_c_biancheng_zhinan_linrui-2024.3.2.0.dist-info/RECORD
